tdms/main.py
tdms-0.1.0.dist-info/LICENSE
tdms-0.1.0.dist-info/METADATA
tdms-0.1.0.dist-info/WHEEL
tdms-0.1.0.dist-info/entry_points.txt
tdms-0.1.0.dist-info/RECORD
